{
  "ruleset_id": "ranked_v0",
  "mode": "solution_race",
  "tick_rate": 60,
  "format": "best_of_3",
  "determinism": { "mode": "park_miller", "pin_seed": true, "pin_fps": true },
  "locked_settings": { "game_speed": "normal", "pause": false, "fast_forward": false },
  "map_pool": {
    "rule": "non_tutorial",
    "comment": "Non-tutorial levels only: World 1 (intro world) excluded entirely, plus the intro levels at the start of every hub. Built at runtime from the engine LevelManager.",
    "exclude_hubs": [0],
    "per_hub_intro_skip": 1,
    "source": "level_manager_runtime",
    "selection": "relay_index_mod_poolsize"
  },
  "state_hash_interval": 300,
  "tiebreakers": ["completion", "finish_tick", "puzzle_pieces", "items_used", "resets"],
  "validation": { "same_platform": "checkpoint_hashes", "cross_platform": "authoritative_resim" }
}
